typeric/__init__.py
typeric/option.py
typeric/py.typed
typeric/result.py
typeric/wrap_funcs.py
typeric-0.1.8.dist-info/METADATA
typeric-0.1.8.dist-info/WHEEL
typeric-0.1.8.dist-info/entry_points.txt
typeric-0.1.8.dist-info/licenses/LICENSE
typeric-0.1.8.dist-info/RECORD
