Metadata-Version: 2.4
Name: typeric
Version: 0.1.8
Summary: Utility types for Python, such as `Result`, `Option`, etc.
Author-email: dfine <coding@dfine.tech>
License-File: LICENSE
Requires-Python: >=3.13
Requires-Dist: loguru>=0.7.3
